drf_temptoken/__init__.py
drf_temptoken/admin.py
drf_temptoken/apps.py
drf_temptoken/auth.py
drf_temptoken/models.py
drf_temptoken/tests.py
drf_temptoken/urls.py
drf_temptoken/utils.py
drf_temptoken/views.py
drf_temptoken/migrations/0001_initial.py
drf_temptoken/migrations/0002_alter_temptoken_key.py
drf_temptoken/migrations/__init__.py
drf_temptoken/signals/__init__.py
drf_temptoken/signals/receivers.py
drf_temptoken-0.1.2.dist-info/LICENSE
drf_temptoken-0.1.2.dist-info/METADATA
drf_temptoken-0.1.2.dist-info/WHEEL
drf_temptoken-0.1.2.dist-info/top_level.txt
drf_temptoken-0.1.2.dist-info/RECORD
