Metadata-Version: 2.1
Name: drf-temptoken
Version: 0.1.2
Summary: DRF temporary token authentication
Home-page: https://notabug.org/kapustlo/drf-temptoken
Author: Kapustlo
License: UNKNOWN
Keywords: python,python3,django,drf,djangorestframework,django rest framework,token,temptoken,temporary
Platform: UNKNOWN
Classifier: Framework :: Django
Classifier: License :: OSI Approved :: GNU General Public License v3 (GPLv3)
Classifier: Topic :: Internet :: WWW/HTTP
Classifier: Development Status :: 4 - Beta
Classifier: Intended Audience :: Developers
Classifier: Programming Language :: Python :: 3 :: Only
Classifier: Operating System :: OS Independent
Requires-Python: >=3.8
License-File: LICENSE
Requires-Dist: django
Requires-Dist: djangorestframework
